{
  "quickadd:choice:854735a1-2d09-4ca3-8a64-cb0991fc90a9": [
    {
      "modifiers": [
        "Mod",
        "Shift"
      ],
      "key": "B"
    }
  ],
  "cmdr:macro-0": [
    {
      "modifiers": [
        "Ctrl"
      ],
      "key": "1"
    }
  ],
  "quickadd:choice:51b51fd2-0f99-43e9-966e-d1bb0ba7318d": [
    {
      "modifiers": [
        "Mod"
      ],
      "key": "5"
    }
  ],
  "local-backup:run-local-backup": [
    {
      "modifiers": [
        "Mod",
        "Alt",
        "Shift"
      ],
      "key": "S"
    }
  ],
  "obsidian-git:commit": [
    {
      "modifiers": [
        "Alt",
        "Shift"
      ],
      "key": "0"
    }
  ],
  "obsidian-git:push2": [
    {
      "modifiers": [
        "Alt",
        "Shift"
      ],
      "key": "="
    }
  ],
  "keyboard-analyzer:show-shortcuts-analyzer-view": [
    {
      "modifiers": [
        "Alt",
        "Shift"
      ],
      "key": "K"
    }
  ],
  "quickadd:choice:4faed75d-0124-4991-be0e-9a1bf7504ef1": [
    {
      "modifiers": [
        "Alt",
        "Shift"
      ],
      "key": "T"
    }
  ],
  "quickadd:choice:c1d9db9a-cb16-4abc-be8e-2b6236276988": [
    {
      "modifiers": [
        "Alt"
      ],
      "key": "T"
    }
  ],
  "quickadd:choice:d1070378-4f3e-4801-872a-041ef3c87568": [
    {
      "modifiers": [
        "Alt",
        "Shift"
      ],
      "key": "1"
    }
  ],
  "quickadd:choice:99b16dcb-f920-42d7-89ad-196b6e4d2f51": [
    {
      "modifiers": [
        "Alt",
        "Shift"
      ],
      "key": "2"
    }
  ],
  "highlightr-plugin:Yellow": [
    {
      "modifiers": [
        "Alt"
      ],
      "key": "Y"
    }
  ],
  "obsidian-linter:lint-file": [
    {
      "modifiers": [
        "Alt",
        "Shift"
      ],
      "key": "L"
    }
  ],
  "find-and-replace-in-selection:find-and-replace-in-selection": [
    {
      "modifiers": [
        "Alt",
        "Mod",
        "Shift"
      ],
      "key": "F"
    }
  ],
  "obsidian-git:pull": [
    {
      "modifiers": [
        "Alt",
        "Shift"
      ],
      "key": "-"
    }
  ],
  "global-search-and-replace:search-and-replace": [
    {
      "modifiers": [
        "Mod",
        "Shift"
      ],
      "key": "F"
    }
  ]
}